ddgmail.py
ddgmail-0.1.7.dist-info/LICENSE
ddgmail-0.1.7.dist-info/METADATA
ddgmail-0.1.7.dist-info/WHEEL
ddgmail-0.1.7.dist-info/entry_points.txt
ddgmail-0.1.7.dist-info/top_level.txt
ddgmail-0.1.7.dist-info/RECORD
