Metadata-Version: 2.1
Name: ddgmail
Version: 0.1.7
Summary: A command line tool to use DuckDuckGo's E-mail forwarding service
Home-page: https://github.com/rany2/ddgmail
Author: rany
Author-email: ranygh@riseup.net
License: UNKNOWN
Platform: UNKNOWN
Classifier: License :: OSI Approved :: GNU General Public License v3 (GPLv3)
Classifier: Programming Language :: Python :: 3
Classifier: Operating System :: OS Independent
License-File: LICENSE
Requires-Dist: Click
Requires-Dist: requests
Requires-Dist: setuptools (>=42.0.0)
